geo_dskit/__init__.py
geo_dskit/cmip.py
geo_dskit/core/types.py
geo_dskit/netcdf.py
geo_dskit/utils/io.py
geo_dskit/utils/log.py
geo_dskit/utils/path.py
geodskit-0.2.0.dist-info/LICENSE
geodskit-0.2.0.dist-info/METADATA
geodskit-0.2.0.dist-info/WHEEL
geodskit-0.2.0.dist-info/RECORD
