Metadata-Version: 2.3
Name: GeoDSKit
Version: 0.2.0
Summary: A modern comprehensive geographic datasets handler kit.
License: MIT
Author: SongshGeo
Author-email: songshgeo@gmail.com
Requires-Python: >=3.8.1,<3.12
Classifier: License :: OSI Approved :: MIT License
Classifier: Programming Language :: Python :: 3
Classifier: Programming Language :: Python :: 3.9
Classifier: Programming Language :: Python :: 3.10
Classifier: Programming Language :: Python :: 3.11
Provides-Extra: netcdf
Requires-Dist: click (>=8)
Requires-Dist: future-annotations (>=1.0.0)
Requires-Dist: netCDF4 (>=1) ; extra == "netcdf"
Requires-Dist: typing-extensions (>=4.12.2)
Requires-Dist: xarray (>=2023) ; extra == "netcdf"
